tiebamd/__init__.py
tiebamd/api.py
tiebamd/assets.py
tiebamd/cli.py
tiebamd/crawl.py
tiebamd/exceptions.py
tiebamd/utils.py
tiebamd-0.1.1.dist-info/entry_points.txt
tiebamd-0.1.1.dist-info/LICENSE
tiebamd-0.1.1.dist-info/WHEEL
tiebamd-0.1.1.dist-info/METADATA
tiebamd-0.1.1.dist-info/RECORD
