Metadata-Version: 2.1
Name: tiebamd
Version: 0.1.1
Summary: 指定下载百度贴吧的某个帖子为 Markdown 文件
Home-page: https://github.com/zombie110year/tiebamd
License: GPL-3.0-only
Author: zombie110year
Author-email: zombie110year@outlook.com
Requires-Python: >=3.6,<4.0
Classifier: License :: OSI Approved :: GNU General Public License v3 (GPLv3)
Classifier: Programming Language :: Python :: 3
Classifier: Programming Language :: Python :: 3.6
Classifier: Programming Language :: Python :: 3.7
Classifier: Programming Language :: Python :: 3.8
Classifier: Programming Language :: Python :: 3.9
Requires-Dist: aiodns (>=2.0.0,<3.0.0)
Requires-Dist: aiohttp (>=3.7.3,<4.0.0)
Requires-Dist: colorama (>=0.4.4,<0.5.0)
Requires-Dist: requests (>=2.25.1,<3.0.0)
Requires-Dist: tqdm (>=4.56.0,<5.0.0)
